youtube_py2/__init__.py
youtube_py2/analytics.cp310-win_amd64.pyd
youtube_py2/analytics.pyi
youtube_py2/async_api.cp310-win_amd64.pyd
youtube_py2/async_api.pyi
youtube_py2/auth.cp310-win_amd64.pyd
youtube_py2/auth.pyi
youtube_py2/binary_hashes.json
youtube_py2/captions.cp310-win_amd64.pyd
youtube_py2/captions.pyi
youtube_py2/channel.cp310-win_amd64.pyd
youtube_py2/channel.pyi
youtube_py2/cli.cp310-win_amd64.pyd
youtube_py2/cli.pyi
youtube_py2/comment.cp310-win_amd64.pyd
youtube_py2/comment.pyi
youtube_py2/export.cp310-win_amd64.pyd
youtube_py2/export.pyi
youtube_py2/license.cp310-win_amd64.pyd
youtube_py2/license.pyi
youtube_py2/live.cp310-win_amd64.pyd
youtube_py2/live.pyi
youtube_py2/localization.cp310-win_amd64.pyd
youtube_py2/localization.pyi
youtube_py2/logging.cp310-win_amd64.pyd
youtube_py2/logging.pyi
youtube_py2/membership.cp310-win_amd64.pyd
youtube_py2/membership.pyi
youtube_py2/pagination.cp310-win_amd64.pyd
youtube_py2/pagination.pyi
youtube_py2/playlist.cp310-win_amd64.pyd
youtube_py2/playlist.pyi
youtube_py2/pubsub.cp310-win_amd64.pyd
youtube_py2/pubsub.pyi
youtube_py2/video.cp310-win_amd64.pyd
youtube_py2/video.pyi
youtube_py2-1.0.27.dist-info/licenses/LICENSE
youtube_py2-1.0.27.dist-info/METADATA
youtube_py2-1.0.27.dist-info/WHEEL
youtube_py2-1.0.27.dist-info/top_level.txt
youtube_py2-1.0.27.dist-info/RECORD
