Metadata-Version: 2.4
Name: youtube_py2
Version: 1.0.27
Summary: YouTube Data API v3 Python Wrapper Library (py2)
Home-page: https://github.com/Himarry/youtube.py2
Author: Himarry
Author-email: 
License: MIT
Platform: UNKNOWN
Requires-Python: >=3.8
License-File: LICENSE
Dynamic: home-page
Dynamic: license-file
Dynamic: requires-python
